[
  {
    "slug": "openclaw",
    "title": "OpenClaw",
    "summary": "A practical starting runtime for learners who want a controllable local assistant environment.",
    "supportTier": "stable",
    "maturityLabel": "Most production-ready of the learning runtimes",
    "beginnerFriendliness": "high",
    "setupComplexity": "medium",
    "setupTime": "30-45 minutes",
    "bestFor": ["first runtime setup", "local assistant experiments", "controlled workflow builds"],
    "recommendedFor": ["beginners who want the safest first runtime", "learners building a local-first spine project", "students who want clearer debugging loops"],
    "avoidIf": ["you need an ultra-lightweight experiment on constrained hardware", "you want persistence-focused memory behavior before mastering the basics"],
    "deploymentPaths": ["local machine", "Docker", "VPS after validation"],
    "interfaceOptions": ["CLI", "local service endpoint", "single-channel assistant"],
    "supportNotes": "Use this as the academy default unless the learner has a very specific runtime constraint.",
    "pros": ["Strong default beginner path", "Good local control", "Fits practical setup lessons well"],
    "cons": ["Still requires environment discipline", "Can feel operationally heavy for absolute non-technical learners"]
  },
  {
    "slug": "hermes-agent",
    "title": "Hermes Agent / Hermet",
    "summary": "A persistence-oriented runtime for learners exploring memory-aware assistants.",
    "supportTier": "emerging",
    "maturityLabel": "Promising but requires more operational care",
    "beginnerFriendliness": "medium",
    "setupComplexity": "high",
    "setupTime": "45-60 minutes",
    "bestFor": ["persistent assistants", "memory patterns", "study and ops helpers"],
    "recommendedFor": ["learners ready to compare short-lived sessions with persistent behavior", "builders exploring memory-aware assistant design", "intermediate runtime labs"],
    "avoidIf": ["this is your first runtime install", "you still need a low-friction confidence-building setup"],
    "deploymentPaths": ["local machine", "Docker", "remote host with careful config"],
    "interfaceOptions": ["CLI", "memory-aware service endpoint", "ops assistant workflows"],
    "supportNotes": "Use after OpenClaw foundations or when the curriculum specifically teaches persistence and memory validation.",
    "pros": ["Good for persistence experiments", "Teaches memory-aware system thinking"],
    "cons": ["More operational complexity", "Not the safest default first runtime"]
  },
  {
    "slug": "nanoclaw",
    "title": "NanoClaw",
    "summary": "A lighter runtime variant for constrained or more experimental local setups.",
    "supportTier": "experimental",
    "maturityLabel": "Use for comparison and exploration, not the default beginner path",
    "beginnerFriendliness": "low",
    "setupComplexity": "medium",
    "setupTime": "20-35 minutes",
    "bestFor": ["runtime comparison", "lightweight experiments", "claw-verse exploration"],
    "recommendedFor": ["comparison labs", "learners curious about tradeoffs in constrained runtime design", "advanced experimentation tracks"],
    "avoidIf": ["you want the safest beginner path", "you need stable support expectations for a capstone"],
    "deploymentPaths": ["local machine", "lightweight container"],
    "interfaceOptions": ["CLI", "minimal local service"],
    "supportNotes": "Position this as a deliberate comparison exercise rather than the first runtime learners should bet on.",
    "pros": ["Good for comparison learning", "Interesting constrained-runtime experiments"],
    "cons": ["Low beginner fit", "Higher support risk", "Should not be the default path for new learners"]
  }
]
